mias_search/__init__.py
mias_search/__main__.py
mias_search/processing.py
ntcir_mias_search/__init__.py
ntcir_mias_search/__main__.py
ntcir_mias_search/abstract.py
ntcir_mias_search/eval.py
ntcir_mias_search/facade.py
ntcir_mias_search/query.py
ntcir_mias_search/test_topic.py
ntcir_mias_search/topic.py
ntcir_mias_search/util.py
ntcir_mias_search/view.py
ntcir_mias_search/webmias.py
ntcir_mias_search-0.2.2.dist-info/LICENSE.txt
ntcir_mias_search-0.2.2.dist-info/METADATA
ntcir_mias_search-0.2.2.dist-info/RECORD
ntcir_mias_search-0.2.2.dist-info/WHEEL
ntcir_mias_search-0.2.2.dist-info/entry_points.txt
ntcir_mias_search-0.2.2.dist-info/top_level.txt
