Metadata-Version: 2.1
Name: ntcir-mias-search
Version: 0.2.2
Summary: 
Home-page: https://github.com/MIR-MU/ntcir-mias-search
Author: Vit Novotny
Maintainer: Vit Novotny
License: MIT
Project-URL: Source, https://github.com/MIR-MU/ntcir-mias-search
Keywords: ntcir mias math_information_retrieval
Platform: UNKNOWN
Classifier: Development Status :: 4 - Beta
Classifier: Environment :: Console
Classifier: Intended Audience :: Science/Research
Classifier: License :: OSI Approved :: MIT License
Classifier: Operating System :: OS Independent
Classifier: Programming Language :: Python :: 3.4
Classifier: Topic :: Scientific/Engineering :: Mathematics
Classifier: Topic :: Text Processing :: Markup :: XML
Requires-Python: ~= 3.4
Requires-Dist: tqdm (~=4.23.3)
Requires-Dist: lxml (~=4.2.1)
Requires-Dist: matplotlib (~=2.2.2)
Requires-Dist: numpy (~=1.14.3)
Requires-Dist: requests (~=2.18.4)
